fastrobo/__init__.py
fastrobo-0.0.1.dist-info/METADATA
fastrobo-0.0.1.dist-info/WHEEL
fastrobo-0.0.1.dist-info/top_level.txt
fastrobo-0.0.1.dist-info/RECORD
