Metadata-Version: 2.1
Name: fastrobo
Version: 0.0.1
Author-email: Jianglong Ye <jianglong.yeh@gmail.com>
License: MIT
Project-URL: Homepage, https://fastrobo.jianglongye.com/
Project-URL: Repository, https://github.com/jianglongye/fastrobo
Classifier: Programming Language :: Python :: 3
Classifier: Programming Language :: Python :: 3.8
Classifier: Programming Language :: Python :: 3.9
Classifier: Programming Language :: Python :: 3.10
Classifier: Programming Language :: Python :: 3.11
Classifier: Programming Language :: Python :: 3.12
Classifier: License :: OSI Approved :: MIT License
Classifier: Operating System :: OS Independent
Requires-Python: >=3.8
Requires-Dist: typing-extensions
Requires-Dist: numpy
